pyfloat/__init__.py
pyfloat/pyfloat.py
pyfloat-0.0.1.dist-info/LICENSE
pyfloat-0.0.1.dist-info/METADATA
pyfloat-0.0.1.dist-info/WHEEL
pyfloat-0.0.1.dist-info/top_level.txt
pyfloat-0.0.1.dist-info/RECORD
